chrome_boss/__init__.py
chrome_boss/element.py
chrome_boss/tab.py
chrome_boss/shared/__init__.py
chrome_boss-0.5.0.dist-info/METADATA
chrome_boss-0.5.0.dist-info/WHEEL
chrome_boss-0.5.0.dist-info/top_level.txt
chrome_boss-0.5.0.dist-info/RECORD
